{"inkVersion":21,"root":[["^El uso de la mi habilidad me está haciendo pasar factura... ","#","^speaker:John ","/#","#","^portrait:John_old ","/#","#","^layout:L","/#","\n","^Me noto más débil, parezco un señor de 90 años. ","#","^speaker:John ","/#","#","^portrait:John_old ","/#","#","^layout:L","/#","\n","^Si vuelvo hacer uso de la habilidad, creo que no habrá vuelta atrás... ","#","^speaker:John ","/#","#","^portrait:John_old ","/#","#","^layout:L","/#","\n","^Será el fin de mi vida. ","#","^speaker:John ","/#","#","^portrait:John_old ","/#","#","^layout:L","/#","\n","^Pero, piensa que si la usas una vez más podrás vengarte de tu hijo al que tanto amabas. ","#","^speaker:Subconsciente ","/#","#","^portrait:Subconsciente_neutral ","/#","#","^layout:R","/#","\n","^Puedes encontrar, junto a Charles, al asesino y matarlo. Así dejarás de sufrir y martirizarte por la muerte de tu hijo. ","#","^speaker:Subconsciente ","/#","#","^portrait:Subconsciente_neutral ","/#","#","^layout:R","/#","\n","^¿Quieres que sacrifique mi vida por vengarme de la muerte de mi hijo? ","#","^speaker:John ","/#","#","^portrait:John_old ","/#","#","^layout:L","/#","\n","^Es lo mejor que puedes hacer John. Pero es tu decisión. ","#","^speaker:Subconsciente ","/#","#","^portrait:Subconsciente_neutral ","/#","#","^layout:R","/#","\n",["done",{"#f":5,"#n":"g-0"}],null],"done",{"#f":1}],"listDefs":{}}